citmre/__int__.py
citmre/__main__.py
citmre/citmre_fun.py
cITMre-0.1.0.dist-info/LICENCE.txt
cITMre-0.1.0.dist-info/METADATA
cITMre-0.1.0.dist-info/WHEEL
cITMre-0.1.0.dist-info/top_level.txt
cITMre-0.1.0.dist-info/RECORD
