Metadata-Version: 2.1
Name: cITMre
Version: 0.1.0
Summary: The Colombian Index Tool (Market Rate Exchange) package downloads the Colombian Market Rate from the source: Portal de Datos Abiertos <www.datos.gov.co>
Home-page: https://sergiofinances.github.io/citmre_development_python/
Author: ['Sergio Andrés Sierra Luján', 'David Esteban Rodríguez Guevara']
Author-email: ['sergiochess95@gmail.com', 'davestss@hotmail.com']
License: MIT
Keywords: finances,econometric,stochastic processes
Classifier: Development Status :: 3 - Alpha
Classifier: Intended Audience :: Education
Classifier: Intended Audience :: Science/Research
Classifier: Topic :: Utilities
Classifier: License :: OSI Approved :: MIT License
Classifier: Programming Language :: Python :: 3
License-File: LICENCE.txt
Requires-Dist: requests
Requires-Dist: pandas
Requires-Dist: numpy
Requires-Dist: plotly
Requires-Dist: lxml
Requires-Dist: bs4
